{"_type":"export","__export_format":4,"__export_date":"2023-03-05T12:51:21.952Z","__export_source":"insomnia.desktop.app:v2022.7.5","resources":[{"_id":"req_e0ae408e229b4ffc9108d01f7df1677f","parentId":"fld_609a609c6b1a4617a0184bba820c69f1","modified":1674483556954,"created":1672734026101,"url":"{{ _.protocol }}://{{ _.host }}/operations/","name":"List","description":"","method":"GET","body":{},"parameters":[{"id":"pair_ca3e4793e9d14061af60a409c8e17fd1","name":"json","value":"true","description":""}],"headers":[],"authentication":{},"metaSortKey":-1672734129297.25,"isPrivate":false,"settingStoreCookies":true,"settingSendCookies":true,"settingDisableRenderRequestBody":false,"settingEncodeUrl":true,"settingRebuildPath":true,"settingFollowRedirects":"global","_type":"request"},{"_id":"fld_609a609c6b1a4617a0184bba820c69f1","parentId":"wrk_d2b422b1107a40c78fa4c774350d3003","modified":1672734023081,"created":1672734023081,"name":"Operations","description":"","environment":{},"environmentPropertyOrder":null,"metaSortKey":-1672734023081,"_type":"request_group"},{"_id":"wrk_d2b422b1107a40c78fa4c774350d3003","parentId":null,"modified":1672048525768,"created":1651222792187,"name":"PhoenixC2","description":"","scope":"collection","_type":"workspace"},{"_id":"req_54b5be494d174bf6a8153c6645c7ed20","parentId":"fld_609a609c6b1a4617a0184bba820c69f1","modified":1674483575671,"created":1674483570833,"url":"{{ _.protocol }}://{{ _.host }}/operations/current","name":"Get current operation","description":"","method":"GET","body":{},"parameters":[{"id":"pair_ca3e4793e9d14061af60a409c8e17fd1","name":"json","value":"true","description":""}],"headers":[],"authentication":{},"metaSortKey":-1672734127577.3125,"isPrivate":false,"settingStoreCookies":true,"settingSendCookies":true,"settingDisableRenderRequestBody":false,"settingEncodeUrl":true,"settingRebuildPath":true,"settingFollowRedirects":"global","_type":"request"},{"_id":"req_0b31c0f13b3a47cbb0353eb0266a1df2","parentId":"fld_609a609c6b1a4617a0184bba820c69f1","modified":1675187132719,"created":1675187088199,"url":"{{ _.protocol }}://{{ _.host }}/operations/{{ _.id }}/picture","name":"Picture","description":"","method":"GET","body":{},"parameters":[{"id":"pair_695cbe5c45a04a18b63bb6a05bd6d0aa","name":"json","value":"true","description":""}],"headers":[],"authentication":{},"metaSortKey":-1672734126717.3438,"isPrivate":false,"settingStoreCookies":true,"settingSendCookies":true,"settingDisableRenderRequestBody":false,"settingEncodeUrl":true,"settingRebuildPath":true,"settingFollowRedirects":"global","_type":"request"},{"_id":"req_29fc2178425b4f65a93c48d19db538f7","parentId":"fld_609a609c6b1a4617a0184bba820c69f1","modified":1675187140601,"created":1675187104877,"url":"{{ _.protocol }}://{{ _.host }}/operations/{{ _.id }}/picture","name":"Set Picture","description":"","method":"POST","body":{"mimeType":"multipart/form-data","params":[{"id":"pair_a4479c1bcf2c49c59f4456f08efb54be","name":"profile-picture","value":"","description":"","type":"file","fileName":"/home/screamz/Pictures/red-tree.jpg"}]},"parameters":[{"id":"pair_0a139d9e3aaf45bf954ee76a9576aa95","name":"json","value":"true","description":""}],"headers":[{"name":"Content-Type","value":"multipart/form-data","id":"pair_96bbdedee9fb470b81e3232c2dd2459a"}],"authentication":{},"metaSortKey":-1672734126287.3594,"isPrivate":false,"settingStoreCookies":true,"settingSendCookies":true,"settingDisableRenderRequestBody":false,"settingEncodeUrl":true,"settingRebuildPath":true,"settingFollowRedirects":"global","_type":"request"},{"_id":"req_eb37cee416fb4485af89e35011758af9","parentId":"fld_609a609c6b1a4617a0184bba820c69f1","modified":1675187146821,"created":1675187120830,"url":"{{ _.protocol }}://{{ _.host }}/operations/{{ _.id }}/picture","name":"Remove Picture","description":"","method":"DELETE","body":{"mimeType":"multipart/form-data","params":[]},"parameters":[{"id":"pair_0a139d9e3aaf45bf954ee76a9576aa95","name":"json","value":"true","description":""}],"headers":[{"name":"Content-Type","value":"multipart/form-data","id":"pair_96bbdedee9fb470b81e3232c2dd2459a"}],"authentication":{},"metaSortKey":-1672734126072.3672,"isPrivate":false,"settingStoreCookies":true,"settingSendCookies":true,"settingDisableRenderRequestBody":false,"settingEncodeUrl":true,"settingRebuildPath":true,"settingFollowRedirects":"global","_type":"request"},{"_id":"req_7cde3a018b7544d4bd89f859424d4640","parentId":"fld_609a609c6b1a4617a0184bba820c69f1","modified":1675187438481,"created":1672734136177,"url":"{{ _.protocol }}://{{ _.host }}//operations/add","name":"Add","description":"","method":"POST","body":{"mimeType":"multipart/form-data","params":[{"id":"pair_acce283862a9471ea12ffe1bbc53fe2a","name":"name","value":"CoolOperation","description":""},{"id":"pair_6a4a43a6ea7f47d9b0eea74d2e3951c8","name":"description","value":"Hello to the current operation","description":"","type":"text","multiline":"text/x-markdown"},{"id":"pair_0d812e72bba14218af28638dedb6eb6b","name":"expiry","value":"2023-02-23","description":""},{"id":"pair_d74da88204c049b4bd1d3eff906a3c79","name":"picture","value":"","description":"","type":"file","fileName":"/home/screamz/Downloads/test.gif"}]},"parameters":[{"id":"pair_b986c28e834c4dbca8bf30b380ffc01a","name":"json","value":"true","description":""}],"headers":[{"name":"Content-Type","value":"multipart/form-data"}],"authentication":{},"metaSortKey":-1672734125857.375,"isPrivate":false,"settingStoreCookies":true,"settingSendCookies":true,"settingDisableRenderRequestBody":false,"settingEncodeUrl":true,"settingRebuildPath":true,"settingFollowRedirects":"global","_type":"request"},{"_id":"req_05da4196a64741a2945e4a4936ffd9c6","parentId":"fld_609a609c6b1a4617a0184bba820c69f1","modified":1674483096458,"created":1672924620455,"url":"{{ _.protocol }}://{{ _.host }}/operations/{{ _.id }}/remove","name":"Delete","description":"","method":"DELETE","body":{"mimeType":"multipart/form-data","params":[]},"parameters":[{"id":"pair_b986c28e834c4dbca8bf30b380ffc01a","name":"json","value":"true","description":""}],"headers":[{"name":"Content-Type","value":"multipart/form-data"}],"authentication":{},"metaSortKey":-1672734122417.5,"isPrivate":false,"settingStoreCookies":true,"settingSendCookies":true,"settingDisableRenderRequestBody":false,"settingEncodeUrl":true,"settingRebuildPath":true,"settingFollowRedirects":"global","_type":"request"},{"_id":"req_a62cf438156a4469b45f50a9fd48114b","parentId":"fld_609a609c6b1a4617a0184bba820c69f1","modified":1674482621942,"created":1672997220026,"url":"{{ _.protocol }}://{{ _.host }}/operations/{{ _.id }}/edit","name":"Edit","description":"","method":"PUT","body":{"mimeType":"multipart/form-data","params":[{"id":"pair_d64e5491c38243568276291b22b86dab","name":"expiry","value":"2023-01-27","description":""}]},"parameters":[{"id":"pair_b986c28e834c4dbca8bf30b380ffc01a","name":"json","value":"true","description":""}],"headers":[{"name":"Content-Type","value":"multipart/form-data"}],"authentication":{},"metaSortKey":-1672734108658,"isPrivate":false,"settingStoreCookies":true,"settingSendCookies":true,"settingDisableRenderRequestBody":false,"settingEncodeUrl":true,"settingRebuildPath":true,"settingFollowRedirects":"global","_type":"request"},{"_id":"req_a8ce21f8551f42cdac7a35f64204b1df","parentId":"fld_609a609c6b1a4617a0184bba820c69f1","modified":1674740392734,"created":1672998431826,"url":"{{ _.protocol }}://{{ _.host }}/operations/{{ _.id }}/assign","name":"Assign User","description":"","method":"POST","body":{"mimeType":"multipart/form-data","params":[{"id":"pair_acce283862a9471ea12ffe1bbc53fe2a","name":"user_id","value":"3","description":""}]},"parameters":[{"id":"pair_b986c28e834c4dbca8bf30b380ffc01a","name":"json","value":"true","description":""}],"headers":[{"name":"Content-Type","value":"multipart/form-data"}],"authentication":{},"metaSortKey":-1672734053620,"isPrivate":false,"settingStoreCookies":true,"settingSendCookies":true,"settingDisableRenderRequestBody":false,"settingEncodeUrl":true,"settingRebuildPath":true,"settingFollowRedirects":"global","_type":"request"},{"_id":"req_27a0c09efe7b4a118ee6ec155e190667","parentId":"fld_609a609c6b1a4617a0184bba820c69f1","modified":1675187075908,"created":1672998528080,"url":"{{ _.protocol }}://{{ _.host }}/operations/{{ _.id }}/unassign","name":"Unassign User","description":"","method":"DELETE","body":{"mimeType":"multipart/form-data","params":[{"id":"pair_acce283862a9471ea12ffe1bbc53fe2a","name":"user_id","value":"1","description":""}]},"parameters":[{"id":"pair_b986c28e834c4dbca8bf30b380ffc01a","name":"json","value":"true","description":""}],"headers":[{"name":"Content-Type","value":"multipart/form-data"}],"authentication":{},"metaSortKey":-1672734039860.5,"isPrivate":false,"settingStoreCookies":true,"settingSendCookies":true,"settingDisableRenderRequestBody":false,"settingEncodeUrl":true,"settingRebuildPath":true,"settingFollowRedirects":"global","_type":"request"},{"_id":"req_4c188790b27844329c66b1e3eacbaa2d","parentId":"fld_609a609c6b1a4617a0184bba820c69f1","modified":1672998597586,"created":1672998543389,"url":"{{ _.protocol }}://{{ _.host }}/operations/{{ _.id }}/add_subnet","name":"Add Subnet","description":"","method":"POST","body":{"mimeType":"multipart/form-data","params":[{"id":"pair_acce283862a9471ea12ffe1bbc53fe2a","name":"subnet","value":"192.168.178.0/24","description":""}]},"parameters":[{"id":"pair_b986c28e834c4dbca8bf30b380ffc01a","name":"json","value":"true","description":""}],"headers":[{"name":"Content-Type","value":"multipart/form-data"}],"authentication":{},"metaSortKey":-1672734032980.75,"isPrivate":false,"settingStoreCookies":true,"settingSendCookies":true,"settingDisableRenderRequestBody":false,"settingEncodeUrl":true,"settingRebuildPath":true,"settingFollowRedirects":"global","_type":"request"},{"_id":"req_3142b15c3b6b4d3196dbc699891ddfc1","parentId":"fld_609a609c6b1a4617a0184bba820c69f1","modified":1675187168976,"created":1672998616696,"url":"{{ _.protocol }}://{{ _.host }}/operations/{{ _.id }}/remove_subnet","name":"Remove Subnet","description":"","method":"DELETE","body":{"mimeType":"multipart/form-data","params":[{"id":"pair_acce283862a9471ea12ffe1bbc53fe2a","name":"subnet","value":"192.168.178.0/24","description":""}]},"parameters":[{"id":"pair_b986c28e834c4dbca8bf30b380ffc01a","name":"json","value":"true","description":""}],"headers":[{"name":"Content-Type","value":"multipart/form-data"}],"authentication":{},"metaSortKey":-1672734029540.875,"isPrivate":false,"settingStoreCookies":true,"settingSendCookies":true,"settingDisableRenderRequestBody":false,"settingEncodeUrl":true,"settingRebuildPath":true,"settingFollowRedirects":"global","_type":"request"},{"_id":"req_e08d0ee126e74394b9a9398a7e419978","parentId":"fld_609a609c6b1a4617a0184bba820c69f1","modified":1672998684217,"created":1672998651059,"url":"{{ _.protocol }}://{{ _.host }}/operations/{{ _.id }}/change","name":"Change current Operation","description":"","method":"PUT","body":{"mimeType":"multipart/form-data","params":[]},"parameters":[{"id":"pair_b986c28e834c4dbca8bf30b380ffc01a","name":"json","value":"true","description":""}],"headers":[{"name":"Content-Type","value":"multipart/form-data"}],"authentication":{},"metaSortKey":-1672734027820.9375,"isPrivate":false,"settingStoreCookies":true,"settingSendCookies":true,"settingDisableRenderRequestBody":false,"settingEncodeUrl":true,"settingRebuildPath":true,"settingFollowRedirects":"global","_type":"request"},{"_id":"req_10c0de22b8e140638cc83a53451d7c09","parentId":"fld_0553129e29bd4dcfb55cb17a8bbbc022","modified":1678020249948,"created":1651222807929,"url":"{{ _.protocol }}://{{ _.host }}/auth/login","name":"Login","description":"","method":"POST","body":{"mimeType":"application/x-www-form-urlencoded","params":[{"id":"pair_963f412c496f44c4beaf398421171534","name":"username","value":"phoenix","description":""},{"id":"pair_28117b2cb2e3434d83d743f43b3aca5f","name":"password","value":"pxPyG'(?,O","description":""}]},"parameters":[{"id":"pair_6afe11a908d448a09fde59d219832816","name":"json","value":"true","description":""},{"id":"pair_5e7511529c7c426098577c9a96fec3f6","name":"","value":"","description":""}],"headers":[{"name":"Content-Type","value":"application/x-www-form-urlencoded","id":"pair_2d3e2ce927c84ebc84a2e1753f227ac9"}],"authentication":{},"metaSortKey":-1651952680078,"isPrivate":false,"settingStoreCookies":true,"settingSendCookies":true,"settingDisableRenderRequestBody":false,"settingEncodeUrl":true,"settingRebuildPath":true,"settingFollowRedirects":"global","_type":"request"},{"_id":"fld_0553129e29bd4dcfb55cb17a8bbbc022","parentId":"wrk_d2b422b1107a40c78fa4c774350d3003","modified":1669663298389,"created":1651244672108,"name":"Auth","description":"","environment":{},"environmentPropertyOrder":null,"metaSortKey":-1663784267245,"_type":"request_group"},{"_id":"req_793dbaf8acad4c6a8ccd5138689f8335","parentId":"fld_0553129e29bd4dcfb55cb17a8bbbc022","modified":1672997648475,"created":1651952680028,"url":"{{ _.protocol }}://{{ _.host }}/auth/logout","name":"Logout","description":"","method":"GET","body":{},"parameters":[{"id":"pair_3ec8d0810643490a89b5461d42cbdfb2","name":"json","value":"true","description":""}],"headers":[],"authentication":{},"metaSortKey":-1651952680028,"isPrivate":false,"settingStoreCookies":true,"settingSendCookies":true,"settingDisableRenderRequestBody":false,"settingEncodeUrl":true,"settingRebuildPath":true,"settingFollowRedirects":"global","_type":"request"},{"_id":"req_d2b2a481c94148fb956ca95474f8af14","parentId":"fld_34a96e59d46340949bb42328ca72fb9a","modified":1675087728262,"created":1651696632390,"url":"{{ _.protocol }}://{{ _.host }}/listeners/","name":"List","description":"","method":"GET","body":{},"parameters":[{"id":"pair_703512bf4113451980fe1bb6836f727c","name":"json","value":"true","description":""},{"id":"pair_d9885e8135aa427fbcb5d8174a6e5798","name":"all","value":"true","description":"","disabled":false}],"headers":[],"authentication":{},"metaSortKey":-1651696654127.125,"isPrivate":false,"settingStoreCookies":true,"settingSendCookies":true,"settingDisableRenderRequestBody":false,"settingEncodeUrl":true,"settingRebuildPath":true,"settingFollowRedirects":"global","_type":"request"},{"_id":"fld_34a96e59d46340949bb42328ca72fb9a","parentId":"wrk_d2b422b1107a40c78fa4c774350d3003","modified":1669663302317,"created":1651244604433,"name":"Listeners","description":"","environment":{},"environmentPropertyOrder":null,"metaSortKey":-1663784267207.5,"_type":"request_group"},{"_id":"req_dbb149d7fd484ae0836a200abf42e4e9","parentId":"fld_34a96e59d46340949bb42328ca72fb9a","modified":1674483076497,"created":1662979082894,"url":"{{ _.protocol }}://{{ _.host }}/listeners/available","name":"Available","description":"","method":"GET","body":{},"parameters":[{"id":"pair_703512bf4113451980fe1bb6836f727c","name":"json","value":"true","description":""},{"id":"pair_0a7589be586f4b29997565ba1696a269","name":"type","value":"all","description":""}],"headers":[],"authentication":{},"metaSortKey":-1651696654124.7812,"isPrivate":false,"settingStoreCookies":true,"settingSendCookies":true,"settingDisableRenderRequestBody":false,"settingEncodeUrl":true,"settingRebuildPath":true,"settingFollowRedirects":"global","_type":"request"},{"_id":"req_52297714b0a14651a879467d27b0d741","parentId":"fld_34a96e59d46340949bb42328ca72fb9a","modified":1677961632095,"created":1651243692805,"url":"{{ _.protocol }}://{{ _.host }}/listeners/add","name":"Add","description":"","method":"POST","body":{"mimeType":"application/x-www-form-urlencoded","params":[{"id":"pair_63af1e407c354c42af9ea76409f254a9","name":"type","value":"http-reverse","description":""},{"id":"pair_c1c5bb8897d3439683ac7b6b6a1b2977","name":"name","value":"NoSSLListener2","description":""},{"id":"pair_8adfe357044f485ea0f0b5781d57a061","name":"address","value":"wlp10s0f3u4","description":""},{"id":"pair_e489fb859eb7466488ffdf27f9b6af1a","name":"port","value":"10000","description":""},{"id":"pair_2c8ea47177054345b2a36fa58410e630","name":"ssl","value":"false","description":""},{"id":"pair_4f12b0fb96094505b473d2579381c69f","name":"limit","value":"5","description":""}]},"parameters":[{"id":"pair_2b66524370f64c5b859d7b95fbd240a3","name":"json","value":"true","description":""},{"id":"pair_f33866721a1548039c56aa41a2530074","name":"is_interface","value":"true","description":""}],"headers":[{"name":"Content-Type","value":"application/x-www-form-urlencoded","id":"pair_06bbda202122404e9b78c60ebd0a74f0"}],"authentication":{},"metaSortKey":-1651696654122.4375,"isPrivate":false,"settingStoreCookies":true,"settingSendCookies":true,"settingDisableRenderRequestBody":false,"settingEncodeUrl":true,"settingRebuildPath":true,"settingFollowRedirects":"global","_type":"request"},{"_id":"req_b9e1f094d3e649209894014b72ca0481","parentId":"fld_34a96e59d46340949bb42328ca72fb9a","modified":1674483104540,"created":1651244630052,"url":"{{ _.protocol }}://{{ _.host }}/listeners/{{ _.id }}/remove","name":"Delete","description":"","method":"DELETE","body":{"mimeType":"multipart/form-data","params":[{"id":"pair_89feed60a7ce44d9aad05003975362bd","name":"stop","value":"true","description":""}]},"parameters":[{"id":"pair_da27e6a326fa440b88d13e24aa6decd6","name":"json","value":"true","description":""},{"id":"pair_080bbd0ff264406596320eda0ea26f13","name":"id","value":"1","description":""}],"headers":[{"name":"Content-Type","value":"multipart/form-data","id":"pair_a547037702e9458cb4b5104651539d0f"}],"authentication":{},"metaSortKey":-1651696654120.0938,"isPrivate":false,"settingStoreCookies":true,"settingSendCookies":true,"settingDisableRenderRequestBody":false,"settingEncodeUrl":true,"settingRebuildPath":true,"settingFollowRedirects":"global","_type":"request"},{"_id":"req_1844c447e6fd419ebf7455cf17d22170","parentId":"fld_34a96e59d46340949bb42328ca72fb9a","modified":1678020651761,"created":1651244635732,"url":"{{ _.protocol }}://{{ _.host }}/listeners/{{ _.id }}/edit","name":"Edit","description":"","method":"PUT","body":{"mimeType":"multipart/form-data","params":[{"id":"pair_d95837686cdb48edb47c43aba72c0ee6","name":"port","value":"9999","description":""}]},"parameters":[{"id":"pair_02bd44730ae44edc8b0c41055cd0b52f","name":"json","value":"true","description":""},{"id":"pair_129a53195a4e4a4299ec8dfc9ff3e3af","name":"id","value":"2","description":""},{"id":"pair_86cb662c17024011b10ddb4d45f59466","name":"restart","value":"false","description":""}],"headers":[{"name":"Content-Type","value":"multipart/form-data","id":"pair_909b40b9ecb744f49f17e248eeb7e922"}],"authentication":{},"metaSortKey":-1651696654117.75,"isPrivate":false,"settingStoreCookies":true,"settingSendCookies":true,"settingDisableRenderRequestBody":false,"settingEncodeUrl":true,"settingRebuildPath":true,"settingFollowRedirects":"global","_type":"request"},{"_id":"req_c020c3d15f114964be1050239abed432","parentId":"fld_34a96e59d46340949bb42328ca72fb9a","modified":1672997746411,"created":1651696654099,"url":"{{ _.protocol }}://{{ _.host }}/listeners/{{ _.id }}/start","name":"Start","description":"","method":"POST","body":{},"parameters":[{"id":"pair_0d979bbdc8554e94b6452c8811499ea0","name":"json","value":"true","description":""}],"headers":[],"authentication":{},"metaSortKey":-1651696654099,"isPrivate":false,"settingStoreCookies":true,"settingSendCookies":true,"settingDisableRenderRequestBody":false,"settingEncodeUrl":true,"settingRebuildPath":true,"settingFollowRedirects":"global","_type":"request"},{"_id":"req_3a90132bae8d4a43a30c401e29ba2940","parentId":"fld_34a96e59d46340949bb42328ca72fb9a","modified":1674483111078,"created":1651696671705,"url":"{{ _.protocol }}://{{ _.host }}/listeners/{{ _.id }}/stop","name":"Stop","description":"","method":"POST","body":{},"parameters":[{"id":"pair_41f95da6bd944ad5abd15fb19bd8cb48","name":"json","value":"true","description":""}],"headers":[],"authentication":{},"metaSortKey":-1651640151803.125,"isPrivate":false,"settingStoreCookies":true,"settingSendCookies":true,"settingDisableRenderRequestBody":false,"settingEncodeUrl":true,"settingRebuildPath":true,"settingFollowRedirects":"global","_type":"request"},{"_id":"req_54488d627de044d7b253459404cba922","parentId":"fld_34a96e59d46340949bb42328ca72fb9a","modified":1677961557714,"created":1662214732904,"url":"{{ _.protocol }}://{{ _.host }}/listeners/{{ _.id }}/restart","name":"Restart","description":"","method":"POST","body":{},"parameters":[{"id":"pair_2b66524370f64c5b859d7b95fbd240a3","name":"json","value":"true","description":""}],"headers":[],"authentication":{},"metaSortKey":-1651583649507.25,"isPrivate":false,"settingStoreCookies":true,"settingSendCookies":true,"settingDisableRenderRequestBody":false,"settingEncodeUrl":true,"settingRebuildPath":true,"settingFollowRedirects":"global","_type":"request"},{"_id":"req_85a51f320e484381bb184c41f931a5e4","parentId":"fld_9f589d17af1a44f9a31fce2d321976b2","modified":1675087912070,"created":1651696690191,"url":"{{ _.protocol }}://{{ _.host }}/stagers/","name":"List","description":"","method":"GET","body":{},"parameters":[{"id":"pair_786cb6e4f9a34b15b22a9a82e7d7b42a","name":"json","value":"true","description":""},{"id":"pair_f2e6baf63de047f89d9076098e2e3422","name":"all","value":"true","description":""}],"headers":[],"authentication":{},"metaSortKey":-1651924271215.5,"isPrivate":false,"settingStoreCookies":true,"settingSendCookies":true,"settingDisableRenderRequestBody":false,"settingEncodeUrl":true,"settingRebuildPath":true,"settingFollowRedirects":"global","_type":"request"},{"_id":"fld_9f589d17af1a44f9a31fce2d321976b2","parentId":"wrk_d2b422b1107a40c78fa4c774350d3003","modified":1674805188881,"created":1651696690166,"name":"Stagers","description":"","environment":{},"environmentPropertyOrder":null,"metaSortKey":-1663784267205.9375,"_type":"request_group"},{"_id":"req_e92a5e1d38ad44f8b1affbe8764cc6e4","parentId":"fld_9f589d17af1a44f9a31fce2d321976b2","modified":1674483409578,"created":1663072054954,"url":"{{ _.protocol }}://{{ _.host }}/stagers/available","name":"Available","description":"","method":"GET","body":{},"parameters":[{"id":"pair_703512bf4113451980fe1bb6836f727c","name":"json","value":"true","description":""},{"id":"pair_0a7589be586f4b29997565ba1696a269","name":"type","value":"http-reverse","description":""}],"headers":[],"authentication":{},"metaSortKey":-1651924271212.375,"isPrivate":false,"settingStoreCookies":true,"settingSendCookies":true,"settingDisableRenderRequestBody":false,"settingEncodeUrl":true,"settingRebuildPath":true,"settingFollowRedirects":"global","_type":"request"},{"_id":"req_4e1b53b9b8dd4b08ba8d6220d0f83dd8","parentId":"fld_9f589d17af1a44f9a31fce2d321976b2","modified":1677961518807,"created":1651696690174,"url":"{{ _.protocol }}://{{ _.host }}/stagers/add","name":"Add","description":"","method":"POST","body":{"mimeType":"application/x-www-form-urlencoded","params":[{"id":"pair_2bec771142f549ecbbdf1eac93bdcb03","name":"listener","value":"1","description":""},{"id":"pair_2482f03d2020470584cb291db8899996","name":"name","value":"go","description":""},{"id":"pair_98e0437a389540589cedf667f6df7cdb","name":"payload","value":"go","description":""}]},"parameters":[{"id":"pair_a5584de6466840a78cdb0090f68eecfb","name":"json","value":"true","description":""}],"headers":[{"name":"Content-Type","value":"application/x-www-form-urlencoded","id":"pair_06bbda202122404e9b78c60ebd0a74f0"}],"authentication":{},"metaSortKey":-1651924271209.25,"isPrivate":false,"settingStoreCookies":true,"settingSendCookies":true,"settingDisableRenderRequestBody":false,"settingEncodeUrl":true,"settingRebuildPath":true,"settingFollowRedirects":"global","_type":"request"},{"_id":"req_522ebd9961fb44e29323c5506252eacb","parentId":"fld_9f589d17af1a44f9a31fce2d321976b2","modified":1674483400396,"created":1651696690183,"url":"{{ _.protocol }}://{{ _.host }}/stagers/{{ _.id }}/remove","name":"Delete","description":"","method":"DELETE","body":{"mimeType":"multipart/form-data","params":[]},"parameters":[{"id":"pair_dae3b0af45454e538c89e8d16076eddd","name":"json","value":"true","description":""}],"headers":[{"name":"Content-Type","value":"multipart/form-data","id":"pair_dc99fb4049414e17af710f1c88498260"}],"authentication":{},"metaSortKey":-1651924271203,"isPrivate":false,"settingStoreCookies":true,"settingSendCookies":true,"settingDisableRenderRequestBody":false,"settingEncodeUrl":true,"settingRebuildPath":true,"settingFollowRedirects":"global","_type":"request"},{"_id":"req_5e4758d88e7d47859ed0ee33f42a6319","parentId":"fld_9f589d17af1a44f9a31fce2d321976b2","modified":1672997674905,"created":1651924271178,"url":"{{ _.protocol }}://{{ _.host }}/stagers/{{ _.id }}/edit","name":"Edit","description":"","method":"PUT","body":{"mimeType":"application/x-www-form-urlencoded","params":[{"id":"pair_1cc0612fa8bd4fa6be95717db23e477b","name":"encoding","value":"raw","description":""}]},"parameters":[{"id":"pair_b1b0b54ae48c4fdb9105ae45929a9d74","name":"json","value":"true","description":""}],"headers":[{"name":"Content-Type","value":"application/x-www-form-urlencoded","id":"pair_99b34787ab6744f8ace401be36710800"}],"authentication":{},"metaSortKey":-1651924271178,"isPrivate":false,"settingStoreCookies":true,"settingSendCookies":true,"settingDisableRenderRequestBody":false,"settingEncodeUrl":true,"settingRebuildPath":true,"settingFollowRedirects":"global","_type":"request"},{"_id":"req_00377773a7194ad0817a3d8cf265415c","parentId":"fld_9f589d17af1a44f9a31fce2d321976b2","modified":1677854902482,"created":1651696952319,"url":"{{ _.protocol }}://{{ _.host }}/stagers/{{ _.id }}/download","name":"Download","description":"","method":"GET","body":{},"parameters":[{"id":"pair_916187e2fd30420da7f07a20f099a2a2","name":"json","value":"true","description":"","disabled":true},{"id":"pair_9f6b0ee99deb4dba9afb1193bb640470","name":"one_liner","value":"true","description":"","disabled":true},{"id":"pair_0730061a1fec4112a584c9b6baa6851b","name":"recompile","value":"true","description":"","disabled":true}],"headers":[],"authentication":{},"metaSortKey":-1651696952319,"isPrivate":false,"settingStoreCookies":true,"settingSendCookies":true,"settingDisableRenderRequestBody":false,"settingEncodeUrl":true,"settingRebuildPath":true,"settingFollowRedirects":"global","_type":"request"},{"_id":"req_ca8438d0aa464e6bbddd93e33aee5b94","parentId":"fld_ef19e5d3a5204a9e87e774614dbc7391","modified":1675087219162,"created":1662158479060,"url":"{{ _.protocol }}://{{ _.host }}/devices","name":"List","description":"","method":"GET","body":{},"parameters":[{"id":"pair_4e1b432b27a14429875efe609333597f","name":"json","value":"true","description":""},{"id":"pair_e17eaaaf61ec49b989164ed0870c152e","name":"all","value":"true","description":""}],"headers":[],"authentication":{},"metaSortKey":-1664177681253,"isPrivate":false,"settingStoreCookies":true,"settingSendCookies":true,"settingDisableRenderRequestBody":false,"settingEncodeUrl":true,"settingRebuildPath":true,"settingFollowRedirects":"global","_type":"request"},{"_id":"fld_ef19e5d3a5204a9e87e774614dbc7391","parentId":"wrk_d2b422b1107a40c78fa4c774350d3003","modified":1669663308532,"created":1652716847791,"name":"Devices","description":"","environment":{},"environmentPropertyOrder":null,"metaSortKey":-1663784267204.375,"_type":"request_group"},{"_id":"req_bc4c98c1fc3b4b6f9c5558ba5db91b63","parentId":"fld_ef19e5d3a5204a9e87e774614dbc7391","modified":1674483137360,"created":1664459429061,"url":"{{ _.protocol }}://{{ _.host }}/devices/{{ _.id }}/clear","name":"Clear","description":"","method":"POST","body":{"mimeType":"multipart/form-data","params":[]},"parameters":[{"id":"pair_2d6ce7cbf47543d39e43a72049897367","name":"json","value":"true","description":"","disabled":false}],"headers":[{"name":"Content-Type","value":"multipart/form-data","id":"pair_1c5021ed5c684df599402424ca845479"}],"authentication":{},"metaSortKey":-1663168069587.75,"isPrivate":false,"settingStoreCookies":true,"settingSendCookies":true,"settingDisableRenderRequestBody":false,"settingEncodeUrl":true,"settingRebuildPath":true,"settingFollowRedirects":"global","_type":"request"},{"_id":"req_e1b0f1fd94c54940a6d04670a2c65d26","parentId":"fld_ef19e5d3a5204a9e87e774614dbc7391","modified":1678010866100,"created":1652716861015,"url":"{{ _.protocol }}://{{ _.host }}/devices/{{ _.id }}/reverse_shell","name":"Reverse Shell","description":"","method":"POST","body":{"mimeType":"multipart/form-data","params":[{"id":"pair_81480124170745f79007b16bbe31df0b","name":"address","value":"192.168.2.184","description":""},{"id":"pair_a2a2690ccfb041f9b66e608c2ab52b2a","name":"port","value":"1234","description":""}]},"parameters":[{"id":"pair_8a01c195a83b41fca14273b98ffcab5e","name":"json","value":"true","description":""}],"headers":[{"name":"Content-Type","value":"multipart/form-data","id":"pair_405e272b53f5407fa3f991a11f236776"}],"authentication":{},"metaSortKey":-1662663263755.125,"isPrivate":false,"settingStoreCookies":true,"settingSendCookies":true,"settingDisableRenderRequestBody":false,"settingEncodeUrl":true,"settingRebuildPath":true,"settingFollowRedirects":"global","_type":"request"},{"_id":"req_a2d707fda19742fbaf4bf0933f8e77fb","parentId":"fld_ef19e5d3a5204a9e87e774614dbc7391","modified":1678009130372,"created":1662158436785,"url":"{{ _.protocol }}://{{ _.host }}/devices/{{ _.id }}/rce","name":"RCE","description":"","method":"POST","body":{"mimeType":"multipart/form-data","params":[{"id":"pair_0b5b686c0d4b448799dae176b7ba6cbe","name":"cmd","value":"whoami","description":""}]},"parameters":[{"id":"pair_b11ea1bb3bcb4a57a347d8f3b99bf552","name":"json","value":"true","description":""}],"headers":[{"name":"Content-Type","value":"multipart/form-data","id":"pair_9e50047617ac4eb6824728f83fd16a8a"}],"authentication":{},"metaSortKey":-1662410860838.8125,"isPrivate":false,"settingStoreCookies":true,"settingSendCookies":true,"settingDisableRenderRequestBody":false,"settingEncodeUrl":true,"settingRebuildPath":true,"settingFollowRedirects":"global","_type":"request"},{"_id":"req_32a391ef54734933be9dc1c1699f31c1","parentId":"fld_ef19e5d3a5204a9e87e774614dbc7391","modified":1672997803889,"created":1662213317774,"url":"{{ _.protocol }}://{{ _.host }}/devices/{{ _.id }}/info","name":"Info","description":"","method":"GET","body":{"mimeType":"multipart/form-data","params":[]},"parameters":[{"id":"pair_4e1b432b27a14429875efe609333597f","name":"json","value":"true","description":""}],"headers":[{"name":"Content-Type","value":"multipart/form-data","id":"pair_9278dd19db68434d967cfe2d7a901c14"}],"authentication":{},"metaSortKey":-1662158457922.5,"isPrivate":false,"settingStoreCookies":true,"settingSendCookies":true,"settingDisableRenderRequestBody":false,"settingEncodeUrl":true,"settingRebuildPath":true,"settingFollowRedirects":"global","_type":"request"},{"_id":"req_d6d04a5b76eb45259e14a1f13794e62c","parentId":"fld_ef19e5d3a5204a9e87e774614dbc7391","modified":1672997812986,"created":1662213348045,"url":"{{ _.protocol }}://{{ _.host }}/devices/{{ _.id }}/dir","name":"Directory Contents","description":"","method":"GET","body":{},"parameters":[{"id":"pair_addbf7cca1b24ce0889c9dc240349a32","name":"json","value":"true","description":""},{"id":"pair_7c69879a8e9a4bc28f5077e43cfd07eb","name":"dir","value":"/home","description":""}],"headers":[],"authentication":{},"metaSortKey":-1662158447353.75,"isPrivate":false,"settingStoreCookies":true,"settingSendCookies":true,"settingDisableRenderRequestBody":false,"settingEncodeUrl":true,"settingRebuildPath":true,"settingFollowRedirects":"global","_type":"request"},{"_id":"req_5de6e052a1034971af2968e63830bd3d","parentId":"fld_ef19e5d3a5204a9e87e774614dbc7391","modified":1678012429711,"created":1662213383872,"url":"{{ _.protocol }}://{{ _.host }}/devices/{{ _.id }}/upload","name":"Upload","description":"","method":"POST","body":{"mimeType":"application/octet-stream","fileName":"/home/screamz/Pictures/mountains.jpg"},"parameters":[{"id":"pair_3196724498d14f088277eab757ff8e54","name":"path","value":"/home/screamz/mountains.jpg","description":""},{"id":"pair_c0eb74a89a3a47238a2dee745208766a","name":"json","value":"true","description":""}],"headers":[{"name":"Content-Type","value":"image/jpeg","id":"pair_405e272b53f5407fa3f991a11f236776"}],"authentication":{},"metaSortKey":-1662158444711.5625,"isPrivate":false,"settingStoreCookies":true,"settingSendCookies":true,"settingDisableRenderRequestBody":false,"settingEncodeUrl":true,"settingRebuildPath":true,"settingFollowRedirects":"global","_type":"request"},{"_id":"req_7462716dac3f413da5f5f1eb99ea8257","parentId":"fld_ef19e5d3a5204a9e87e774614dbc7391","modified":1672997822930,"created":1662213712619,"url":"{{ _.protocol }}://{{ _.host }}/devices/{{ _.id }}/download","name":"Download","description":"","method":"GET","body":{},"parameters":[{"id":"pair_1ce857fbd0ea4db09c7c8eac4cff9f52","name":"path","value":"/home/screamz/Vpn/htb.ovpn","description":""},{"id":"pair_d4608107f0af4362af726d6ded60aace","name":"json","value":"true","description":""}],"headers":[],"authentication":{},"metaSortKey":-1662158442069.375,"isPrivate":false,"settingStoreCookies":true,"settingSendCookies":true,"settingDisableRenderRequestBody":false,"settingEncodeUrl":true,"settingRebuildPath":true,"settingFollowRedirects":"global","_type":"request"},{"_id":"req_c5f10f3b7fc34696bf3ffd14f0f7d196","parentId":"fld_ef19e5d3a5204a9e87e774614dbc7391","modified":1672999711167,"created":1670266473862,"url":"{{ _.protocol }}://{{ _.host }}/devices/{{ _.id }}/module","name":"Module","description":"","method":"POST","body":{"mimeType":"multipart/form-data","params":[{"id":"pair_81480124170745f79007b16bbe31df0b","name":"path","value":"Capturing/Keyboard_Capture","description":""},{"id":"pair_0badbee8e6504763972d600c10709813","name":"method","value":"direct","description":""}]},"parameters":[{"id":"pair_8a01c195a83b41fca14273b98ffcab5e","name":"json","value":"true","description":""}],"headers":[{"name":"Content-Type","value":"multipart/form-data","id":"pair_405e272b53f5407fa3f991a11f236776"}],"authentication":{},"metaSortKey":-1652538912145,"isPrivate":false,"settingStoreCookies":true,"settingSendCookies":true,"settingDisableRenderRequestBody":false,"settingEncodeUrl":true,"settingRebuildPath":true,"settingFollowRedirects":"global","_type":"request"},{"_id":"req_ddbbb56a3bfb45a1865d356c10cc366a","parentId":"fld_4af98e5e392947cc93d47c4ae339461a","modified":1674483188920,"created":1652004732574,"url":"{{ _.protocol }}://{{ _.host }}/users/","name":"List Users","description":"","method":"GET","body":{},"parameters":[{"id":"pair_695cbe5c45a04a18b63bb6a05bd6d0aa","name":"json","value":"true","description":""}],"headers":[],"authentication":{},"metaSortKey":-1652005065485,"isPrivate":false,"settingStoreCookies":true,"settingSendCookies":true,"settingDisableRenderRequestBody":false,"settingEncodeUrl":true,"settingRebuildPath":true,"settingFollowRedirects":"global","_type":"request"},{"_id":"fld_4af98e5e392947cc93d47c4ae339461a","parentId":"wrk_d2b422b1107a40c78fa4c774350d3003","modified":1669663305994,"created":1661725697712,"name":"Users","description":"","environment":{},"environmentPropertyOrder":null,"metaSortKey":-1663784267201.25,"_type":"request_group"},{"_id":"req_dd7eaca878fa425d9767cbc75a5b1aca","parentId":"fld_4af98e5e392947cc93d47c4ae339461a","modified":1674483222684,"created":1674483204946,"url":"{{ _.protocol }}://{{ _.host }}/users/{{ _.id }}/picture","name":"Profile Picture","description":"","method":"GET","body":{},"parameters":[{"id":"pair_695cbe5c45a04a18b63bb6a05bd6d0aa","name":"json","value":"true","description":""}],"headers":[],"authentication":{},"metaSortKey":-1652005065472.5,"isPrivate":false,"settingStoreCookies":true,"settingSendCookies":true,"settingDisableRenderRequestBody":false,"settingEncodeUrl":true,"settingRebuildPath":true,"settingFollowRedirects":"global","_type":"request"},{"_id":"req_7b27e9c6d3e34453a32f56a775a026a3","parentId":"fld_4af98e5e392947cc93d47c4ae339461a","modified":1675876223626,"created":1674729085010,"url":"{{ _.protocol }}://{{ _.host }}/users/{{ _.id }}/picture","name":"Set Profile Picture","description":"","method":"POST","body":{"mimeType":"multipart/form-data","params":[{"id":"pair_a4479c1bcf2c49c59f4456f08efb54be","name":"profile-picture","value":"","description":"","type":"file","fileName":"/home/screamz/Downloads/Screenshot_20230104_205613.png"}]},"parameters":[{"id":"pair_0a139d9e3aaf45bf954ee76a9576aa95","name":"json","value":"true","description":""}],"headers":[{"name":"Content-Type","value":"multipart/form-data","id":"pair_96bbdedee9fb470b81e3232c2dd2459a"}],"authentication":{},"metaSortKey":-1652005065469.375,"isPrivate":false,"settingStoreCookies":true,"settingSendCookies":true,"settingDisableRenderRequestBody":false,"settingEncodeUrl":true,"settingRebuildPath":true,"settingFollowRedirects":"global","_type":"request"},{"_id":"req_0bbdf31758b64ff3b55f72707fd5402a","parentId":"fld_4af98e5e392947cc93d47c4ae339461a","modified":1674654581352,"created":1674654565525,"url":"{{ _.protocol }}://{{ _.host }}/users/{{ _.id }}/picture","name":"Remove Profile Picture","description":"","method":"DELETE","body":{"mimeType":"multipart/form-data","params":[]},"parameters":[{"id":"pair_0a139d9e3aaf45bf954ee76a9576aa95","name":"json","value":"true","description":""}],"headers":[{"name":"Content-Type","value":"multipart/form-data","id":"pair_96bbdedee9fb470b81e3232c2dd2459a"}],"authentication":{},"metaSortKey":-1652005065466.25,"isPrivate":false,"settingStoreCookies":true,"settingSendCookies":true,"settingDisableRenderRequestBody":false,"settingEncodeUrl":true,"settingRebuildPath":true,"settingFollowRedirects":"global","_type":"request"},{"_id":"req_d82c05af103d4b4498f7a658ae8620ea","parentId":"fld_4af98e5e392947cc93d47c4ae339461a","modified":1674740387047,"created":1651952210802,"url":"{{ _.protocol }}://{{ _.host }}/users/add","name":"Add User","description":"","method":"POST","body":{"mimeType":"application/x-www-form-urlencoded","params":[{"id":"pair_a8a4b7524ffb41b6b7a3bec8d7f72509","name":"username","value":"pentester2","description":""},{"id":"pair_74ef616ac6454aaea657529a25468b19","name":"password","value":"jamalsdsdsd","description":""},{"id":"pair_5dd729cefa39488996c3b07caab8df97","name":"admin","value":"true","description":""}]},"parameters":[{"id":"pair_8d69f96b07d443e6b9335b666c8ded6e","name":"json","value":"true","description":""}],"headers":[{"name":"Content-Type","value":"application/x-www-form-urlencoded","id":"pair_0ef0a2cf9e1e4aef8683a3f25125fa8e"}],"authentication":{},"metaSortKey":-1652005065460,"isPrivate":false,"settingStoreCookies":true,"settingSendCookies":true,"settingDisableRenderRequestBody":false,"settingEncodeUrl":true,"settingRebuildPath":true,"settingFollowRedirects":"global","_type":"request"},{"_id":"req_e56eeae2b6b7406199b0cbdbb08a89bf","parentId":"fld_4af98e5e392947cc93d47c4ae339461a","modified":1674483191318,"created":1652005065385,"url":"{{ _.protocol }}://{{ _.host }}/users/{{ _.id }}/remove","name":"Remove User","description":"","method":"DELETE","body":{"mimeType":"multipart/form-data","params":[]},"parameters":[{"id":"pair_0a139d9e3aaf45bf954ee76a9576aa95","name":"json","value":"true","description":""}],"headers":[{"name":"Content-Type","value":"multipart/form-data","id":"pair_96bbdedee9fb470b81e3232c2dd2459a"}],"authentication":{},"metaSortKey":-1652005065447.5,"isPrivate":false,"settingStoreCookies":true,"settingSendCookies":true,"settingDisableRenderRequestBody":false,"settingEncodeUrl":true,"settingRebuildPath":true,"settingFollowRedirects":"global","_type":"request"},{"_id":"req_92759606a2c24f5684f748e91875acd4","parentId":"fld_4af98e5e392947cc93d47c4ae339461a","modified":1677613364936,"created":1652004497540,"url":"{{ _.protocol }}://{{ _.host }}/users/{{ _.id }}/edit","name":"Edit User","description":"","method":"PUT","body":{"mimeType":"application/x-www-form-urlencoded","params":[{"id":"pair_808bd36d83da4f3286227ff98d39559e","name":"password","value":"phoenix","description":""}]},"parameters":[{"id":"pair_13c0902b2ff142c7926be6b6ef6fd787","name":"json","value":"true","description":""}],"headers":[{"name":"Content-Type","value":"application/x-www-form-urlencoded","id":"pair_c1e70fa988c44dc2a4ad491297af942c"}],"authentication":{},"metaSortKey":-1652005065435,"isPrivate":false,"settingStoreCookies":true,"settingSendCookies":true,"settingDisableRenderRequestBody":false,"settingEncodeUrl":true,"settingRebuildPath":true,"settingFollowRedirects":"global","_type":"request"},{"_id":"req_7bc686f5b41a467fa0b357a630fab556","parentId":"fld_4af98e5e392947cc93d47c4ae339461a","modified":1674483267535,"created":1674483249919,"url":"{{ _.protocol }}://{{ _.host }}/users/{{ _.id }}/reset_api_key","name":"Reset Api Key","description":"","method":"PUT","body":{"mimeType":"application/x-www-form-urlencoded","params":[]},"parameters":[{"id":"pair_13c0902b2ff142c7926be6b6ef6fd787","name":"json","value":"true","description":""}],"headers":[{"name":"Content-Type","value":"application/x-www-form-urlencoded","id":"pair_c1e70fa988c44dc2a4ad491297af942c"}],"authentication":{},"metaSortKey":-1651978872756.5,"isPrivate":false,"settingStoreCookies":true,"settingSendCookies":true,"settingDisableRenderRequestBody":false,"settingEncodeUrl":true,"settingRebuildPath":true,"settingFollowRedirects":"global","_type":"request"},{"_id":"req_15f0f151a97f4cd9acfe018108461c33","parentId":"fld_20f294ec22c8447a96dd047fefcec780","modified":1675087972165,"created":1663784273771,"url":"{{ _.protocol }}://{{ _.host }}/tasks/","name":"List","description":"","method":"GET","body":{},"parameters":[{"id":"pair_703512bf4113451980fe1bb6836f727c","name":"json","value":"true","description":""},{"id":"pair_7eb5a4762c3a4ebe9236b250ce00357b","name":"all","value":"true","description":""}],"headers":[],"authentication":{},"metaSortKey":-1657688003036,"isPrivate":false,"settingStoreCookies":true,"settingSendCookies":true,"settingDisableRenderRequestBody":false,"settingEncodeUrl":true,"settingRebuildPath":true,"settingFollowRedirects":"global","_type":"request"},{"_id":"fld_20f294ec22c8447a96dd047fefcec780","parentId":"wrk_d2b422b1107a40c78fa4c774350d3003","modified":1663784267195,"created":1663784267195,"name":"Tasks","description":"","environment":{},"environmentPropertyOrder":null,"metaSortKey":-1663784267195,"_type":"request_group"},{"_id":"req_becb1ddd9c9c407cbeee0400dfd63d6a","parentId":"fld_20f294ec22c8447a96dd047fefcec780","modified":1678008571027,"created":1664136827328,"url":"{{ _.protocol }}://{{ _.host }}/tasks/all/clear","name":"Clear","description":"","method":"DELETE","body":{"mimeType":"multipart/form-data","params":[]},"parameters":[{"id":"pair_2d6ce7cbf47543d39e43a72049897367","name":"json","value":"true","description":""}],"headers":[{"name":"Content-Type","value":"multipart/form-data","id":"pair_bfb7d0ae4eda47f1a3c09114020bf995"}],"authentication":{},"metaSortKey":-1657688002986,"isPrivate":false,"settingStoreCookies":true,"settingSendCookies":true,"settingDisableRenderRequestBody":false,"settingEncodeUrl":true,"settingRebuildPath":true,"settingFollowRedirects":"global","_type":"request"},{"_id":"req_341bb4ec13194195bf9f7a4b9c8eac43","parentId":"fld_e939fcf992414a5a8ca46c724b0bb47e","modified":1675087723538,"created":1664208487840,"url":"{{ _.protocol }}://{{ _.host }}/logs/","name":"List","description":"","method":"GET","body":{},"parameters":[{"id":"pair_703512bf4113451980fe1bb6836f727c","name":"json","value":"true","description":""},{"id":"pair_139919f16c334cfe9092958652f6538f","name":"all","value":"true","description":""}],"headers":[],"authentication":{},"metaSortKey":-1657688003036,"isPrivate":false,"settingStoreCookies":true,"settingSendCookies":true,"settingDisableRenderRequestBody":false,"settingEncodeUrl":true,"settingRebuildPath":true,"settingFollowRedirects":"global","_type":"request"},{"_id":"fld_e939fcf992414a5a8ca46c724b0bb47e","parentId":"wrk_d2b422b1107a40c78fa4c774350d3003","modified":1664208487838,"created":1664208487838,"name":"Logs","description":"","environment":{},"environmentPropertyOrder":null,"metaSortKey":-1663341612457,"_type":"request_group"},{"_id":"req_a4bd68e9a3784a3c97e6393e1b8f28a3","parentId":"fld_e939fcf992414a5a8ca46c724b0bb47e","modified":1674483433292,"created":1669927016605,"url":"{{ _.protocol }}://{{ _.host }}/logs/read","name":"Read all unseen logs ","description":"","method":"GET","body":{},"parameters":[{"id":"pair_703512bf4113451980fe1bb6836f727c","name":"json","value":"true","description":""}],"headers":[],"authentication":{},"metaSortKey":-1656075114845.75,"isPrivate":false,"settingStoreCookies":true,"settingSendCookies":true,"settingDisableRenderRequestBody":false,"settingEncodeUrl":true,"settingRebuildPath":true,"settingFollowRedirects":"global","_type":"request"},{"_id":"req_48b8ee5f428945ab809eea5fa0f57b0b","parentId":"fld_e939fcf992414a5a8ca46c724b0bb47e","modified":1675187219675,"created":1664208487844,"url":"{{ _.protocol }}://{{ _.host }}/ogs/{{ _.id }}/clear","name":"Clear","description":"","method":"DELETE","body":{"mimeType":"multipart/form-data","params":[]},"parameters":[{"id":"pair_2d6ce7cbf47543d39e43a72049897367","name":"json","value":"true","description":""},{"id":"pair_f70eaa0264ca42a287e4aa615443d954","name":"seen","value":"true","description":""}],"headers":[{"name":"Content-Type","value":"multipart/form-data","id":"pair_4dab6c1b134c495e90c72642185b77d2"}],"authentication":{},"metaSortKey":-1654462226655.5,"isPrivate":false,"settingStoreCookies":true,"settingSendCookies":true,"settingDisableRenderRequestBody":false,"settingEncodeUrl":true,"settingRebuildPath":true,"settingFollowRedirects":"global","_type":"request"},{"_id":"req_a035e7f4b3624bc78a3d8b9d23660b2b","parentId":"fld_ecaa2a44111c44e292ebbec9dce4e91d","modified":1676642057528,"created":1676641998422,"url":"{{ _.protocol }}://{{ _.host }}/info","name":"Info","description":"","method":"GET","body":{},"parameters":[{"id":"pair_5933d161eff146fd96cfb5a94a93b9eb","name":"json","value":"true","description":""}],"headers":[],"authentication":{},"metaSortKey":-1662898976036.4688,"isPrivate":false,"settingStoreCookies":true,"settingSendCookies":true,"settingDisableRenderRequestBody":false,"settingEncodeUrl":true,"settingRebuildPath":true,"settingFollowRedirects":"global","_type":"request"},{"_id":"fld_ecaa2a44111c44e292ebbec9dce4e91d","parentId":"wrk_d2b422b1107a40c78fa4c774350d3003","modified":1662898957719,"created":1662898957719,"name":"Misc","description":"","environment":{},"environmentPropertyOrder":null,"metaSortKey":-1662898957719,"_type":"request_group"},{"_id":"req_41ebe9a765c14732b0da0c5d947be80a","parentId":"fld_ecaa2a44111c44e292ebbec9dce4e91d","modified":1674483456893,"created":1662898990439,"url":"{{ _.protocol }}://{{ _.host }}/misc/interfaces","name":"Interfaces","description":"","method":"GET","body":{},"parameters":[],"headers":[],"authentication":{},"metaSortKey":-1662898973577.5,"isPrivate":false,"settingStoreCookies":true,"settingSendCookies":true,"settingDisableRenderRequestBody":false,"settingEncodeUrl":true,"settingRebuildPath":true,"settingFollowRedirects":"global","_type":"request"},{"_id":"req_779b5d34d7994d4399a762948e50d95a","parentId":"fld_ecaa2a44111c44e292ebbec9dce4e91d","modified":1674483503073,"created":1674483482570,"url":"{{ _.protocol }}://{{ _.host }}/misc/ping","name":"Ping","description":"","method":"GET","body":{},"parameters":[],"headers":[],"authentication":{},"metaSortKey":-1662898970767.25,"isPrivate":false,"settingStoreCookies":true,"settingSendCookies":true,"settingDisableRenderRequestBody":false,"settingEncodeUrl":true,"settingRebuildPath":true,"settingFollowRedirects":"global","_type":"request"},{"_id":"req_e5135fe3cc95452f846027cd30568448","parentId":"fld_ecaa2a44111c44e292ebbec9dce4e91d","modified":1674483507113,"created":1668105534140,"url":"{{ _.protocol }}://{{ _.host }}/misc/downloads/test","name":"Downloads","description":"","method":"GET","body":{},"parameters":[],"headers":[],"authentication":{},"metaSortKey":-1662898969362.125,"isPrivate":false,"settingStoreCookies":true,"settingSendCookies":true,"settingDisableRenderRequestBody":false,"settingEncodeUrl":true,"settingRebuildPath":true,"settingFollowRedirects":"global","_type":"request"},{"_id":"req_8287fd29d9584918950b6e533dadf53a","parentId":"fld_ecaa2a44111c44e292ebbec9dce4e91d","modified":1674483538174,"created":1668105625262,"url":"{{ _.protocol }}://{{ _.host }}/misc/uploads/clear","name":"Clear Uploads","description":"","method":"POST","body":{},"parameters":[{"id":"pair_f7a1055bd3de4e52a010509dc173d0c7","name":"json","value":"true","description":""}],"headers":[],"authentication":{},"metaSortKey":-1662713839239.9375,"isPrivate":false,"settingStoreCookies":true,"settingSendCookies":true,"settingDisableRenderRequestBody":false,"settingEncodeUrl":true,"settingRebuildPath":true,"settingFollowRedirects":"global","_type":"request"},{"_id":"req_166fcfdc6efe4e07a7847f9a3b313239","parentId":"fld_ecaa2a44111c44e292ebbec9dce4e91d","modified":1672998038408,"created":1664177681203,"url":"{{ _.protocol }}://{{ _.host }}/misc/downloads/clear","name":"Clear Downloads","description":"","method":"POST","body":{},"parameters":[{"id":"pair_f7a1055bd3de4e52a010509dc173d0c7","name":"json","value":"true","description":""}],"headers":[],"authentication":{},"metaSortKey":-1662528709117.75,"isPrivate":false,"settingStoreCookies":true,"settingSendCookies":true,"settingDisableRenderRequestBody":false,"settingEncodeUrl":true,"settingRebuildPath":true,"settingFollowRedirects":"global","_type":"request"},{"_id":"env_b361236819c4c76b5249c334d9a09afcaa2a2624","parentId":"wrk_d2b422b1107a40c78fa4c774350d3003","modified":1664209492603,"created":1651222792195,"name":"Base Environment","data":{},"dataPropertyOrder":{},"color":null,"isPrivate":false,"metaSortKey":1651222792195,"_type":"environment"},{"_id":"jar_b361236819c4c76b5249c334d9a09afcaa2a2624","parentId":"wrk_d2b422b1107a40c78fa4c774350d3003","modified":1678020250585,"created":1651222792196,"name":"Default Jar","cookies":[{"key":"session","value":"eyJhcGlfa2V5IjoiNjk2ZDgxYzItYmI1My0xMWVkLThjYTYtMDA1MDU2YzAwMDAxIn0.ZASOmg.Z2cRqlC-IzKJTDVbztNWzPWwf08","domain":"localhost","path":"/","httpOnly":true,"hostOnly":true,"creation":"2022-12-29T09:30:47.382Z","lastAccessed":"2023-03-05T12:44:10.584Z","id":"15137603393031918"},{"key":"operation","value":"1","expires":"2033-01-27T13:59:59.000Z","maxAge":315360000,"domain":"localhost","path":"/","hostOnly":true,"creation":"2023-01-06T09:56:05.188Z","lastAccessed":"2023-01-30T13:59:59.371Z","id":"046570223743446215"},{"key":"session","value":".eJwNh7EKAjEMQP-l3OjQ5Ehz6ewkCA4ujm3Soqhcz4IO4r_bt7z3vu5mLsLOtdT7Z32NcS3frWLs14QUIgY_mPxBn4_T2Vo9vvfrdplSEamEnECqKOQFGMAvRqOFh0vwqppxNmXNleciRuhFCAm4uN8fGikkOA.Y9JU_g.x76YXBYgheT1GxMtWKC280B71aQ","domain":"0.0.0.0","path":"/","httpOnly":true,"hostOnly":true,"creation":"2023-01-26T10:25:02.728Z","lastAccessed":"2023-01-26T10:25:02.728Z","id":"7969828700508226"},{"key":"session","value":"eyJhcGlfa2V5IjoiZmYzODk3MTItYTdkMi0xMWVkLTgwNmYtMDI0MmFjMTEwMWM5In0.Y-PXjA.nlEb7hg8XqB3mCO284bKTbUpe3Q","domain":"phoenixc2-production.up.railway.app","path":"/","httpOnly":true,"hostOnly":true,"creation":"2023-02-08T16:59:27.789Z","lastAccessed":"2023-02-08T17:10:36.838Z","id":"5154481251358634"}],"_type":"cookie_jar"},{"_id":"spc_707e16d43f004329b183b134c192bc2d","parentId":"wrk_d2b422b1107a40c78fa4c774350d3003","modified":1651222792190,"created":1651222792190,"fileName":"Phoenix Framework","contents":"","contentType":"yaml","_type":"api_spec"},{"_id":"env_1349c96e348d458686504b66f911a0db","parentId":"env_b361236819c4c76b5249c334d9a09afcaa2a2624","modified":1677958640255,"created":1651696741012,"name":"PhoenixC2","data":{"protocol":"http","host":"localhost:8080","id":"1"},"dataPropertyOrder":{"&":["protocol","host","id"]},"color":"#ff3c00","isPrivate":false,"metaSortKey":1651696741012,"_type":"environment"}]}